Workbook

Sheet 1. Sintesi Esecutiva
A1: INDICATORE | B1: VALORE
A2: ═══ FINANZIAMENTI ═══
A3: Capitale iniziale | B3: €13,000
A4: Soci (3 founder x €5.000) | B4: €15,000
A5: Bando R&D Horizon Europe | B5: €80,000
A6: Smart&Start Invitalia | B6: €60,000
A7: TOTALE RISORSE 2026 | B7: €168,000
A9: ═══ CRESCITA CLIENTI ═══
A10: Comuni 2026 | B10: ='8. Parametri'!E3 -> 1
A11: Comuni 2030 | B11: ='8. Parametri'!E7 -> 35
A12: Crescita comuni 5 anni | B12: +48 comuni
A13: Utenti 2026 | B13: 100
A14: Utenti 2030 | B14: 7500
A15: Crescita utenti 5 anni | B15: +7400 utenti
A17: ═══ RICAVI ═══
A18: Ricavi 2026 | B18: ='2. Conto Economico'!E2 -> 33000
A19: Ricavi 2030 | B19: ='2. Conto Economico'!E6 -> 1568470.6
A20: CAGR Ricavi | B20: +97.1% annuo
A22: ═══ REDDITIVITÀ ═══
A23: EBITDA 2026 | B23: ='2. Conto Economico'!T2 -> -64340
A24: EBITDA 2030 | B24: ='2. Conto Economico'!T6 -> 1023567
A25: Margine EBITDA 2030 | B25: 68.4%
A26: Break-even EBITDA | B26: 2028
A28: Utile 2026 | B28: ='2. Conto Economico'!AA2 -> -68740
A29: Utile 2030 | B29: €680,173
A31: ═══ CASSA E SOSTENIBILITÀ ═══
A32: Cassa minima (anno) | B32: 2027
A33: Cassa minima (importo) | B33: €37,050
A34: Cassa finale 2030 | B34: €739,847
A35: Break-even Cash Flow | B35: 2029
A37: ═══ TEAM ═══
A38: Team 2026 | B38: 3 persone (founder)
A39: Team 2030 | B39: 6 persone (team completo)

Sheet 2. Conto Economico
A1: Anno | B1: Ricavi Comuni (recurring) | C1: Ricavi Utenti (recurring) | D1: Setup Fee (non recurring) | E1: TOTALE RICAVI | F1: Contributi R&D | G1: VALORE PRODUZIONE | H1: Costo Cloud/Hosting | I1: Costo API/Maps | J1: TOTALE COSTI VARIABILI | K1: MARGINE CONTRIBUZIONE | L1: Costo Personale | M1: (di cui TFR) | N1: Product Development | O1: Customer Acquisition | P1: Systems & Operations | Q1: Networking & Biz Dev | R1: Admin & Corporate | S1: TOTALE COSTI FISSI | T1: EBITDA | U1: Ammortamenti Materiali | V1: Ammortamenti Immateriali | W1: EBIT | X1: Interessi Prestito | Y1: RISULTATO ANTE IMPOSTE | Z1: Imposte (27.9%) | AA1: RISULTATO ESERCIZIO
A2: 2026 | B2: ='4. Ricavi Dettaglio'!D2 -> 12000 | C2: ='4. Ricavi Dettaglio'!E2 -> 18000 | D2: ='4. Ricavi Dettaglio'!F2 -> 3000 | E2: =B2+C2+D2 -> 33000 | F2: 20000 | G2: =E2+F2 -> 53000 | H2: ='4. Ricavi Dettaglio'!C2*'8. Parametri'!$B$16*12 -> 3000 | I2: ='8. Parametri'!$B$17*(1+'8. Parametri'!$B$18)^0 -> 1500 | J2: =H2+I2 -> 4500 | K2: =G2-J2 -> 48500 | L2: 81840 | M2: 0 | N2: 9000 | O2: 5000 | P2: 6000 | Q2: 6000 | R2: 5000 | S2: =L2+N2+O2+P2+Q2+R2 -> 112840 | T2: =K2-S2 -> -64340 | U2: 600 | V2: 2000 | W2: =T2-U2-V2 -> -66940 | X2: 1800 | Y2: =W2-X2 -> -68740 | Z2: =IF(Y2>0,Y2*0.279,0) -> 0 | AA2: =Y2-Z2 -> -68740
A3: 2027 | B3: ='4. Ricavi Dettaglio'!D3 -> 50400 | C3: ='4. Ricavi Dettaglio'!E3 -> 74160 | D3: ='4. Ricavi Dettaglio'!F3 -> 9000 | E3: =B3+C3+D3 -> 133560 | F3: 35000 | G3: =E3+F3 -> 168560 | H3: ='4. Ricavi Dettaglio'!C3*'8. Parametri'!$B$16*12 -> 12000 | I3: ='8. Parametri'!$B$17*(1+'8. Parametri'!$B$18)^1 -> 1725 | J3: =H3+I3 -> 13725 | K3: =G3-J3 -> 154835 | L3: 100800 | M3: 5800 | N3: 15000 | O3: 12000 | P3: 10000 | Q3: 12000 | R3: 6000 | S3: =L3+N3+O3+P3+Q3+R3 -> 155800 | T3: =K3-S3 -> -965 | U3: 1800 | V3: 3200 | W3: =T3-U3-V3 -> -5965 | X3: 1350 | Y3: =W3-X3 -> -7315 | Z3: =IF(Y3>0,Y3*0.279,0) -> 0 | AA3: =Y3-Z3 -> -7315
A4: 2028 | B4: ='4. Ricavi Dettaglio'!D4 -> 132300 | C4: ='4. Ricavi Dettaglio'!E4 -> 190962 | D4: ='4. Ricavi Dettaglio'!F4 -> 18000 | E4: =B4+C4+D4 -> 341262 | F4: 45000 | G4: =E4+F4 -> 386262 | H4: ='4. Ricavi Dettaglio'!C4*'8. Parametri'!$B$16*12 -> 30000 | I4: ='8. Parametri'!$B$17*(1+'8. Parametri'!$B$18)^2 -> 1983.75 | J4: =H4+I4 -> 31983.75 | K4: =G4-J4 -> 354278.25 | L4: 204400 | M4: 11940 | N4: 24000 | O4: 22000 | P4: 14000 | Q4: 24000 | R4: 7000 | S4: =L4+N4+O4+P4+Q4+R4 -> 295400 | T4: =K4-S4 -> 58878.25 | U4: 3400 | V4: 4000 | W4: =T4-U4-V4 -> 51478.25 | X4: 900 | Y4: =W4-X4 -> 50578.25 | Z4: =IF(Y4>0,Y4*0.279,0) -> 14111.332 | AA4: =Y4-Z4 -> 36466.918
A5: 2029 | B5: ='4. Ricavi Dettaglio'!D5 -> 277830 | C5: ='4. Ricavi Dettaglio'!E5 -> 472058.06 | D5: ='4. Ricavi Dettaglio'!F5 -> 30000 | E5: =B5+C5+D5 -> 779888.06 | F5: 40000 | G5: =E5+F5 -> 819888.06 | H5: ='4. Ricavi Dettaglio'!C5*'8. Parametri'!$B$16*12 -> 72000 | I5: ='8. Parametri'!$B$17*(1+'8. Parametri'!$B$18)^3 -> 2281.3125 | J5: =H5+I5 -> 74281.312 | K5: =G5-J5 -> 745606.75 | L5: 249600 | M5: 11060 | N5: 28000 | O5: 30000 | P5: 18000 | Q5: 32000 | R5: 8000 | S5: =L5+N5+O5+P5+Q5+R5 -> 365600 | T5: =K5-S5 -> 380006.75 | U5: 5400 | V5: 5200 | W5: =T5-U5-V5 -> 369406.75 | X5: 450 | Y5: =W5-X5 -> 368956.75 | Z5: =IF(Y5>0,Y5*0.279,0) -> 102938.93 | AA5: =Y5-Z5 -> 266017.82
A6: 2030 | B6: ='4. Ricavi Dettaglio'!D6 -> 510512.62 | C6: ='4. Ricavi Dettaglio'!E6 -> 1012957.9 | D6: ='4. Ricavi Dettaglio'!F6 -> 45000 | E6: =B6+C6+D6 -> 1568470.6 | F6: 20000 | G6: =E6+F6 -> 1588470.6 | H6: ='4. Ricavi Dettaglio'!C6*'8. Parametri'!$B$16*12 -> 150000 | I6: ='8. Parametri'!$B$17*(1+'8. Parametri'!$B$18)^4 -> 2623.5094 | J6: =H6+I6 -> 152623.51 | K6: =G6-J6 -> 1435847 | L6: 269280 | M6: 13860 | N6: 32000 | O6: 38000 | P6: 22000 | Q6: 42000 | R6: 9000 | S6: =L6+N6+O6+P6+Q6+R6 -> 412280 | T6: =K6-S6 -> 1023567 | U6: 7800 | V6: 6800 | W6: =T6-U6-V6 -> 1008967 | X6: 0 | Y6: =W6-X6 -> 1008967 | Z6: =IF(Y6>0,Y6*0.279,0) -> 281501.81 | AA6: =Y6-Z6 -> 727465.24

Sheet 3. Flusso di Cassa
A1: Anno | B1: Comuni clienti | C1: Utenti privati | D1: Cassa Iniziale | E1: Risultato Esercizio | F1: Crediti R&D (-) | G1: Incassi R&D (+) | H1: TFR (+) | I1: Ammortamenti (+) | J1: FLUSSO OPERATIVO | K1: Var. Crediti (-) | L1: Var. Debiti (+) | M1: FLUSSO CCN | N1: CAPEX (-) | O1: Pagamento Imposte (-) | P1: Investimento Soci (+) | Q1: Anticipo Bando R&D (+) | R1: Prestito Smart&Start (+) | S1: Rimborso Prestito (-) | T1: FLUSSO FINANZIARIO | U1: CASH FLOW NETTO | V1: Cassa Finale
A2: 2026 | B2: ='4. Ricavi Dettaglio'!B2 -> 1 | C2: ='4. Ricavi Dettaglio'!C2 -> 500 | D2: 13000 | E2: ='2. Conto Economico'!AA2 -> -68740 | F2: -20000 | G2: 8000 | H2: 0 | I2: ='2. Conto Economico'!U2+'2. Conto Economico'!V2 -> 2600 | J2: =E2+F2+G2+H2+I2 -> -78140 | K2: =-(('2. Conto Economico'!E2*45/365)-0) -> -4068.4932 | L2: =(('5. Costi Dettaglio'!B2*60/365)-0) -> 739.72603 | M2: =K2+L2 -> -3328.7671 | N2: -13000 | O2: 0 | P2: 15000 | Q2: 80000 | R2: 60000 | S2: 0 | T2: =P2+Q2+R2+S2 -> 155000 | U2: =J2+M2+N2+O2+T2 -> 60531.233 | V2: =D2+U2 -> 73531.233
A3: 2027 | B3: ='4. Ricavi Dettaglio'!B3 -> 4 | C3: ='4. Ricavi Dettaglio'!C3 -> 2000 | D3: =V2 -> 73531.233 | E3: ='2. Conto Economico'!AA3 -> -7315 | F3: -35000 | G3: 26000 | H3: 5800 | I3: ='2. Conto Economico'!U3+'2. Conto Economico'!V3 -> 5000 | J3: =E3+F3+G3+H3+I3 -> -5515 | K3: =-(('2. Conto Economico'!E3*45/365)-('2. Conto Economico'!E2*45/365)) -> -12397.808 | L3: =(('5. Costi Dettaglio'!B3*60/365)-('5. Costi Dettaglio'!B2*60/365)) -> 1516.4384 | M3: =K3+L3 -> -10881.37 | N3: -11000 | O3: 0 | P3: 0 | Q3: 0 | R3: 0 | S3: -15000 | T3: =P3+Q3+R3+S3 -> -15000 | U3: =J3+M3+N3+O3+T3 -> -42396.37 | V3: =D3+U3 -> 31134.863
A4: 2028 | B4: ='4. Ricavi Dettaglio'!B4 -> 10 | C4: ='4. Ricavi Dettaglio'!C4 -> 5000 | D4: =V3 -> 31134.863 | E4: ='2. Conto Economico'!AA4 -> 36466.918 | F4: -45000 | G4: 39000 | H4: 10360 | I4: ='2. Conto Economico'!U4+'2. Conto Economico'!V4 -> 7400 | J4: =E4+F4+G4+H4+I4 -> 48226.918 | K4: =-(('2. Conto Economico'!E4*45/365)-('2. Conto Economico'!E3*45/365)) -> -25607.096 | L4: =(('5. Costi Dettaglio'!B4*60/365)-('5. Costi Dettaglio'!B3*60/365)) -> 3001.4384 | M4: =K4+L4 -> -22605.658 | N4: -12000 | O4: 0 | P4: 0 | Q4: 0 | R4: 0 | S4: -15000 | T4: =P4+Q4+R4+S4 -> -15000 | U4: =J4+M4+N4+O4+T4 -> -1378.7393 | V4: =D4+U4 -> 29756.124
A5: 2029 | B5: ='4. Ricavi Dettaglio'!B5 -> 20 | C5: ='4. Ricavi Dettaglio'!C5 -> 12000 | D5: =V4 -> 29756.124 | E5: ='2. Conto Economico'!AA5 -> 266017.82 | F5: -40000 | G5: 43000 | H5: 11060 | I5: ='2. Conto Economico'!U5+'2. Conto Economico'!V5 -> 10600 | J5: =E5+F5+G5+H5+I5 -> 290677.82 | K5: =-(('2. Conto Economico'!E5*45/365)-('2. Conto Economico'!E4*45/365)) -> -54077.186 | L5: =(('5. Costi Dettaglio'!B5*60/365)-('5. Costi Dettaglio'!B4*60/365)) -> 6953.024 | M5: =K5+L5 -> -47124.162 | N5: -20000 | O5: =-'2. Conto Economico'!Z4 -> -14111.332 | P5: 0 | Q5: 0 | R5: 0 | S5: -15000 | T5: =P5+Q5+R5+S5 -> -15000 | U5: =J5+M5+N5+O5+T5 -> 194442.32 | V5: =D5+U5 -> 224198.45
A6: 2030 | B6: ='4. Ricavi Dettaglio'!B6 -> 35 | C6: ='4. Ricavi Dettaglio'!C6 -> 25000 | D6: =V5 -> 224198.45 | E6: ='2. Conto Economico'!AA6 -> 727465.24 | F6: -20000 | G6: 32000 | H6: 13860 | I6: ='2. Conto Economico'!U6+'2. Conto Economico'!V6 -> 14600 | J6: =E6+F6+G6+H6+I6 -> 767925.24 | K6: =-(('2. Conto Economico'!E6*45/365)-('2. Conto Economico'!E5*45/365)) -> -97222.499 | L6: =(('5. Costi Dettaglio'!B6*60/365)-('5. Costi Dettaglio'!B5*60/365)) -> 12878.169 | M6: =K6+L6 -> -84344.329 | N6: -24000 | O6: =-'2. Conto Economico'!Z5 -> -102938.93 | P6: 0 | Q6: 0 | R6: 0 | S6: -15000 | T6: =P6+Q6+R6+S6 -> -15000 | U6: =J6+M6+N6+O6+T6 -> 541641.98 | V6: =D6+U6 -> 765840.42

Sheet 4. Ricavi Dettaglio
A1: Anno | B1: Comuni clienti | C1: Utenti privati | D1: Ricavi Comuni (recurring) | E1: Ricavi Utenti (recurring) | F1: Setup Fee (non recurring) | G1: TOTALE RICAVI | H1: Contributi R&D | I1: VALORE PRODUZIONE
A2: 2026 | B2: ='8. Parametri'!E3 -> 1 | C2: ='8. Parametri'!F3 -> 500 | D2: =B2*'8. Parametri'!$B$9*(1+'8. Parametri'!$B$10)^(A2-2026) -> 12000 | E2: =C2*'8. Parametri'!$B$11*12*(1+'8. Parametri'!$B$12)^(A2-2026) -> 18000 | F2: =B2*'8. Parametri'!$B$13 -> 3000 | G2: =SUM(D2:F2) -> 33000 | H2: 20000 | I2: =SUM(G2:H2) -> 53000
A3: 2027 | B3: ='8. Parametri'!E4 -> 4 | C3: ='8. Parametri'!F4 -> 2000 | D3: =B3*'8. Parametri'!$B$9*(1+'8. Parametri'!$B$10)^(A3-2026) -> 50400 | E3: =C3*'8. Parametri'!$B$11*12*(1+'8. Parametri'!$B$12)^(A3-2026) -> 74160 | F3: =(B3-B2)*'8. Parametri'!$B$13 -> 9000 | G3: =SUM(D3:F3) -> 133560 | H3: 35000 | I3: =SUM(G3:H3) -> 168560
A4: 2028 | B4: ='8. Parametri'!E5 -> 10 | C4: ='8. Parametri'!F5 -> 5000 | D4: =B4*'8. Parametri'!$B$9*(1+'8. Parametri'!$B$10)^(A4-2026) -> 132300 | E4: =C4*'8. Parametri'!$B$11*12*(1+'8. Parametri'!$B$12)^(A4-2026) -> 190962 | F4: =(B4-B3)*'8. Parametri'!$B$13 -> 18000 | G4: =SUM(D4:F4) -> 341262 | H4: 45000 | I4: =SUM(G4:H4) -> 386262
A5: 2029 | B5: ='8. Parametri'!E6 -> 20 | C5: ='8. Parametri'!F6 -> 12000 | D5: =B5*'8. Parametri'!$B$9*(1+'8. Parametri'!$B$10)^(A5-2026) -> 277830 | E5: =C5*'8. Parametri'!$B$11*12*(1+'8. Parametri'!$B$12)^(A5-2026) -> 472058.06 | F5: =(B5-B4)*'8. Parametri'!$B$13 -> 30000 | G5: =SUM(D5:F5) -> 779888.06 | H5: 40000 | I5: =SUM(G5:H5) -> 819888.06
A6: 2030 | B6: ='8. Parametri'!E7 -> 35 | C6: ='8. Parametri'!F7 -> 25000 | D6: =B6*'8. Parametri'!$B$9*(1+'8. Parametri'!$B$10)^(A6-2026) -> 510512.62 | E6: =C6*'8. Parametri'!$B$11*12*(1+'8. Parametri'!$B$12)^(A6-2026) -> 1012957.9 | F6: =(B6-B5)*'8. Parametri'!$B$13 -> 45000 | G6: =SUM(D6:F6) -> 1568470.6 | H6: 20000 | I6: =SUM(G6:H6) -> 1588470.6

Sheet 5. Costi Dettaglio
A1: Anno | B1: TOTALE COSTI VARIABILI | C1: Costo Personale | D1: (di cui TFR) | E1: Product Development | F1: Customer Acquisition | G1: Systems & Operations | H1: Networking & Biz Dev | I1: Admin & Corporate | J1: TOTALE COSTI FISSI
A2: 2026 | B2: ='4. Ricavi Dettaglio'!C2*'8. Parametri'!$B$16*12+'8. Parametri'!$B$17*(1+'8. Parametri'!$B$18)^(0) -> 4500 | C2: 81840 | D2: 0 | E2: 9000 | F2: 5000 | G2: 6000 | H2: 6000 | I2: 5000 | J2: =C2+SUM(E2:I2) -> 112840
A3: 2027 | B3: ='4. Ricavi Dettaglio'!C3*'8. Parametri'!$B$16*12+'8. Parametri'!$B$17*(1+'8. Parametri'!$B$18)^(1) -> 13725 | C3: 100800 | D3: 5800 | E3: 15000 | F3: 12000 | G3: 10000 | H3: 12000 | I3: 6000 | J3: =C3+SUM(E3:I3) -> 155800
A4: 2028 | B4: ='4. Ricavi Dettaglio'!C4*'8. Parametri'!$B$16*12+'8. Parametri'!$B$17*(1+'8. Parametri'!$B$18)^(2) -> 31983.75 | C4: 204400 | D4: 11940 | E4: 24000 | F4: 22000 | G4: 14000 | H4: 24000 | I4: 7000 | J4: =C4+SUM(E4:I4) -> 295400
A5: 2029 | B5: ='4. Ricavi Dettaglio'!C5*'8. Parametri'!$B$16*12+'8. Parametri'!$B$17*(1+'8. Parametri'!$B$18)^(3) -> 74281.312 | C5: 249600 | D5: 11060 | E5: 28000 | F5: 30000 | G5: 18000 | H5: 32000 | I5: 8000 | J5: =C5+SUM(E5:I5) -> 365600
A6: 2030 | B6: ='4. Ricavi Dettaglio'!C6*'8. Parametri'!$B$16*12+'8. Parametri'!$B$17*(1+'8. Parametri'!$B$18)^(4) -> 152623.51 | C6: 269280 | D6: 13860 | E6: 32000 | F6: 38000 | G6: 22000 | H6: 42000 | I6: 9000 | J6: =C6+SUM(E6:I6) -> 412280

Sheet 6. Team Evolution
A1: Anno | B1: Ruolo | C1: RAL | D1: Tipo Contratto | E1: Costo Aziendale
A2: 2026 | B2: Founder Dev 1 | C2: 22000 | D2: COCOCO | E2: 27280
A3: 2026 | B3: Founder Dev 2 | C3: 22000 | D3: COCOCO | E3: 27280
A4: 2026 | B4: Founder PM | C4: 22000 | D4: COCOCO | E4: 27280
A5: 2027 | B5: Founder Dev 1 | C5: 28000 | D5: APPRENDISTA | E5: 33600
A6: 2027 | B6: Founder Dev 2 | C6: 28000 | D6: APPRENDISTA | E6: 33600
A7: 2027 | B7: Founder PM | C7: 28000 | D7: APPRENDISTA | E7: 33600
A8: 2028 | B8: Founder Dev 1 | C8: 30000 | D8: DIPENDENTE | E8: 40800
A9: 2028 | B9: Founder Dev 2 | C9: 30000 | D9: DIPENDENTE | E9: 40800
A10: 2028 | B10: Founder PM | C10: 30000 | D10: DIPENDENTE | E10: 40800
A11: 2028 | B11: Dev Junior | C11: 28000 | D11: DIPENDENTE | E11: 38080
A12: 2028 | B12: Data Scientist | C12: 32000 | D12: DIPENDENTE | E12: 43520
A13: 2029 | B13: Founder Dev 1 | C13: 32000 | D13: DIPENDENTE | E13: 43520
... A24: 2030 | B24: Commerciale | C24: 30000 | D24: DIPENDENTE | E24: 40800

Sheet 7. Finanziamenti
A1: Anno | B1: Investimento Soci | C1: Anticipo Bando R&D | D1: Prestito Smart&Start | E1: Rimborso Prestito | F1: FLUSSO FINANZIARIO NETTO
A2: 2026 | B2: 15000 | C2: 80000 | D2: 60000 | E2: 0 | F2: 155000
A3: 2027 | B3: 0 | C3: 0 | D3: 0 | E3: -15000 | F3: -15000
A4: 2028 | B4: 0 | C4: 0 | D4: 0 | E4: -15000 | F4: -15000
A5: 2029 | B5: 0 | C5: 0 | D5: 0 | E5: -15000 | F5: -15000
A6: 2030 | B6: 0 | C6: 0 | D6: 0 | E6: -15000 | F6: -15000

Sheet 8. Parametri
A1: PARAMETRO | B1: VALORE | D1: ═══ CRESCITA CLIENTI ANNO PER ANNO ═══
A2: ═══ CLIENTI ═══ | D2: Anno | E2: Comuni | F2: Utenti
A3: Comuni 2026 | B3: 1 | D3: 2026 | E3: 1 | F3: 500
A4: Comuni 2030 | B4: 35 | D4: 2027 | E4: 4 | F4: 2000
A5: Utenti 2026 | B5: 500 | D5: 2028 | E5: 10 | F5: 5000
A6: Utenti 2030 | B6: 25000 | D6: 2029 | E6: 20 | F6: 12000
D7: 2030 | E7: 35 | F7: 25000
A8: ═══ PRICING ═══
A9: Prezzo comune/anno (2026) | B9: 12000
A10: Crescita prezzo comuni | B10: 0.05
A11: Prezzo utente/mese (2026) | B11: 3
A12: Crescita prezzo utenti | B12: 0.03
A13: Setup fee per comune | B13: 3000
A15: ═══ COSTI ═══
A16: Costo cloud per utente/mese | B16: 0.5
A17: Costo API Maps anno base | B17: 1500
A18: Crescita costo API | B18: 0.15
A20: ═══ CAPITALE CIRCOLANTE ═══
A21: Giorni incasso clienti | B21: 45 giorni
A22: Giorni pagamento fornitori | B22: 60 giorni
A24: ═══ FINANZIAMENTI ═══
A25: Capitale iniziale | B25: €13,000
A26: Investimento soci | B26: €15,000
A27: Bando R&D totale | B27: €80,000
A28: Smart&Start totale | B28: €60,000
A29: Rata rimborso annuale | B29: €15,000/anno
